sonicscrewdriver/__init__.py
sonicscrewdriver/gui.py
sonicscrewdriver/presets.py
sonicscrewdriver/sonic_screwdriver.py
sonicscrewdriver/sonification.py
sonicscrewdriver/spectrum.py
sonicscrewdriver/util.py
Sonic_Screwdriver-1.3.6.dist-info/LICENSE
Sonic_Screwdriver-1.3.6.dist-info/METADATA
Sonic_Screwdriver-1.3.6.dist-info/WHEEL
Sonic_Screwdriver-1.3.6.dist-info/top_level.txt
Sonic_Screwdriver-1.3.6.dist-info/RECORD
