Metadata-Version: 2.1
Name: Sonic-Screwdriver
Version: 1.3.6
Summary: Astrophysics outreach tool
Author-email: Harry Addison <ha00871@surrey.ac.uk>
Project-URL: Homepage, https://github.com/HarryAddison/Sonic-Screwdriver
Project-URL: Issues, https://github.com/HarryAddison/Sonic-Screwdriver/issues
Classifier: Programming Language :: Python :: 3
Classifier: License :: OSI Approved :: MIT License
Classifier: Operating System :: OS Independent
Requires-Python: >=3.8
License-File: LICENSE
Requires-Dist: customtkinter
Requires-Dist: matplotlib
Requires-Dist: numpy
Requires-Dist: pandas
Requires-Dist: pillow
Requires-Dist: pygame
Requires-Dist: scikit-learn
Requires-Dist: sonification
Requires-Dist: strauss
Requires-Dist: tensorflow ==2.13.0
Requires-Dist: tables
